Metadata-Version: 2.1
Name: bing_image_downloader
Version: 1.1.1
Summary: Python library to download bulk images from Bing.com
Home-page: https://github.com/gurugaurav/bing_image_downloader
Author: Guru Prasad Singh
Author-email: g.gaurav541@gmail.com
License: UNKNOWN
Keywords: bing,images,scraping,image download,bulk image downloader
Platform: UNKNOWN
Classifier: Programming Language :: Python :: 3
Classifier: License :: OSI Approved :: MIT License
Classifier: Operating System :: OS Independent
